multi_browser_crawler/__init__.py
multi_browser_crawler/__main__.py
multi_browser_crawler/ad_blocker.py
multi_browser_crawler/api_capture.py
multi_browser_crawler/browser.py
multi_browser_crawler/browser_cli.py
multi_browser_crawler/browser_pool.py
multi_browser_crawler/config.py
multi_browser_crawler/context_slot.py
multi_browser_crawler/debug_port_manager.py
multi_browser_crawler/pool_utils.py
multi_browser_crawler/proxy_manager.py
multi_browser_crawler/py.typed
multi_browser_crawler/utils.py
multi_browser_crawler/js/cleanup_aggressive.js
multi_browser_crawler/js/cleanup_minimal.js
multi_browser_crawler/js/cleanup_page.js
multi_browser_crawler/js/cleanup_page_simple.js
multi_browser_crawler/js/clear_storage.js
multi_browser_crawler/js/extract_image.js
multi_browser_crawler/js/network_monitoring.js
multi_browser_crawler-0.5.5.dist-info/licenses/LICENSE
multi_browser_crawler-0.5.5.dist-info/METADATA
multi_browser_crawler-0.5.5.dist-info/WHEEL
multi_browser_crawler-0.5.5.dist-info/top_level.txt
multi_browser_crawler-0.5.5.dist-info/RECORD
