Metadata-Version: 2.4
Name: multi-browser-crawler
Version: 0.5.5
Summary: Focused browser automation package for web scraping and content extraction
Author-email: Spider MCP Team <team@spider-mcp.com>
License-Expression: MIT
Project-URL: Homepage, https://github.com/spider-mcp/multi-browser-crawler
Project-URL: Documentation, https://multi-browser-crawler.readthedocs.io/
Project-URL: Repository, https://github.com/spider-mcp/multi-browser-crawler
Project-URL: Bug Reports, https://github.com/spider-mcp/multi-browser-crawler/issues
Keywords: browser,automation,crawling,scraping,playwright,selenium,web,testing,multiprocess,proxy
Classifier: Development Status :: 4 - Beta
Classifier: Intended Audience :: Developers
Classifier: Operating System :: OS Independent
Classifier: Programming Language :: Python :: 3
Classifier: Programming Language :: Python :: 3.8
Classifier: Programming Language :: Python :: 3.9
Classifier: Programming Language :: Python :: 3.10
Classifier: Programming Language :: Python :: 3.11
Classifier: Programming Language :: Python :: 3.12
Classifier: Topic :: Internet :: WWW/HTTP :: Browsers
Classifier: Topic :: Software Development :: Libraries :: Python Modules
Classifier: Topic :: Software Development :: Testing
Requires-Python: >=3.8
License-File: LICENSE
Requires-Dist: patchright>=1.52.0
Requires-Dist: playwright>=1.40.0
Requires-Dist: undetected-chromedriver>=3.5.0
Requires-Dist: selenium>=4.15.0
Requires-Dist: aiohttp>=3.8.0
Requires-Dist: beautifulsoup4>=4.12.0
Requires-Dist: psutil>=5.9.0
Requires-Dist: lxml>=4.9.0
Requires-Dist: html5lib>=1.1
Requires-Dist: redis>=6.0.0
Provides-Extra: dev
Requires-Dist: pytest>=7.0.0; extra == "dev"
Requires-Dist: pytest-asyncio>=0.21.0; extra == "dev"
Requires-Dist: pytest-cov>=4.0.0; extra == "dev"
Requires-Dist: black>=23.0.0; extra == "dev"
Requires-Dist: flake8>=6.0.0; extra == "dev"
Requires-Dist: mypy>=1.0.0; extra == "dev"
Requires-Dist: pre-commit>=3.0.0; extra == "dev"
Provides-Extra: docs
Requires-Dist: sphinx>=6.0.0; extra == "docs"
Requires-Dist: sphinx-rtd-theme>=1.2.0; extra == "docs"
Requires-Dist: myst-parser>=1.0.0; extra == "docs"
Provides-Extra: performance
Requires-Dist: uvloop>=0.17.0; sys_platform != "win32" and extra == "performance"
Requires-Dist: orjson>=3.8.0; extra == "performance"
Dynamic: license-file
